Metadata-Version: 2.1
Name: matrixcalc
Version: 0.0.2
Summary: user-friendly calculator + algorithms of various matrix operations
Home-page: https://github.com/SMALA-comand/Matrix_calculator
Author: Lev Pambukhchyan
Author-email: leva200211@gmail.com
License: UNKNOWN
Platform: UNKNOWN
Classifier: Programming Language :: Python :: 3.9
Classifier: License :: OSI Approved :: MIT License
Classifier: Operating System :: OS Independent
